LICENSE
README.md
setup.py
certtool/__init__.py
certtool/__main__.py
certtool.egg-info/PKG-INFO
certtool.egg-info/SOURCES.txt
certtool.egg-info/dependency_links.txt
certtool.egg-info/entry_points.txt
certtool.egg-info/requires.txt
certtool.egg-info/top_level.txt